odoo/addons/sale_cart_step/README.rst
odoo/addons/sale_cart_step/__init__.py
odoo/addons/sale_cart_step/__manifest__.py
odoo/addons/sale_cart_step/data/cart_step.xml
odoo/addons/sale_cart_step/i18n/sale_cart_step.pot
odoo/addons/sale_cart_step/models/__init__.py
odoo/addons/sale_cart_step/models/sale_order.py
odoo/addons/sale_cart_step/models/sale_order_cart_step.py
odoo/addons/sale_cart_step/readme/CONTRIBUTORS.rst
odoo/addons/sale_cart_step/readme/DESCRIPTION.rst
odoo/addons/sale_cart_step/security/ir.model.access.csv
odoo/addons/sale_cart_step/static/description/index.html
odoo/addons/sale_cart_step/tests/__init__.py
odoo/addons/sale_cart_step/tests/test_sale_cart_step.py
odoo/addons/sale_cart_step/views/cart_step.xml
odoo/addons/sale_cart_step/views/sale_order.xml
odoo_addon_sale_cart_step-16.0.1.0.0.2.dist-info/METADATA
odoo_addon_sale_cart_step-16.0.1.0.0.2.dist-info/WHEEL
odoo_addon_sale_cart_step-16.0.1.0.0.2.dist-info/top_level.txt
odoo_addon_sale_cart_step-16.0.1.0.0.2.dist-info/RECORD
